[{"body":"","link":"https://clallam.lgbt/","section":"","tags":null,"title":""},{"body":"","link":"https://clallam.lgbt/tags/news/","section":"tags","tags":null,"title":"News"},{"body":"","link":"https://clallam.lgbt/post/","section":"post","tags":["index"],"title":"Posts"},{"body":"","link":"https://clallam.lgbt/tags/","section":"tags","tags":null,"title":"Tags"},{"body":"","link":"https://clallam.lgbt/tags/welcome/","section":"tags","tags":null,"title":"Welcome"},{"body":"Welcome First pages are always interesting because they are quickly out-dated. I am very hopeful about the rapid growth of this site once the foundation is properly complete, and I wish to address the future of Clallam|LGBT:\nTemplate modifications are ongoing for the foreseeable future. The glossary will be designed to expand outwards with no expectation of finite boundaries Events will be updated as we get closer to Pride Season™. I'm always looking for additional content contributors, whether graphics, coders, or writers! ","link":"https://clallam.lgbt/post/blog/welcome/","section":"post","tags":["Welcome","News"],"title":"Welcome"},{"body":"About the Author Cloud Huxley was born in Port Angeles and graduated from Sequim High School in 2003. Cloud uses \u0026quot;she/they\u0026quot; pronouns in all aspects of her life. She works with the public during the day and writes code at night. Cloud is a proud Queer Anarchist who believes that Queer Liberation is just as much an inalienable right as any, and will not ask permission to exist.\nCloud created Clallam|LGBT for the dissemination of Queer resources. The information within these pages is meant to be spread, and it was built from the ground up to accomplish that task.\nTechnology Stack Clallam|LGBT is built on the shoulders of giants.\nHugo static-site generator manages our online resources into a functional site. The Clarity Theme provides the \u0026quot;look \u0026amp; feel\u0026quot;. Hosting is provided by Neocities. The Domain Name was provided by Namecheap. Project source code is available at Github. My design is simple, transparent, and the code is available for study.\nContacting Cloud Cloud may be reached via email: clallamlgbt@gmail.com.\n","link":"https://clallam.lgbt/about/","section":"","tags":null,"title":"About"},{"body":"","link":"https://clallam.lgbt/categories/","section":"categories","tags":null,"title":"Categories"},{"body":"","link":"https://clallam.lgbt/tags/index/","section":"tags","tags":null,"title":"index"},{"body":"","link":"https://clallam.lgbt/series/","section":"series","tags":null,"title":"Series"}]